[
    {
        "id": "1",
        "url": "http://localhost:3000/images/image-1.webp"
    },
    {
        "id": "2",
        "url": "http://localhost:3000/images/image-2.webp"
    },
    {
        "id": "3",
        "url": "http://localhost:3000/images/image-3.webp"
    },
    {
        "id": "4",
        "url": "http://localhost:3000/images/image-4.webp"
    },
    {
        "id": "5",
        "url": "http://localhost:3000/images/image-5.webp"
    },
    {
        "id": "6",
        "url": "http://localhost:3000/images/image-6.webp"
    },
    {
        "id": "7",
        "url": "http://localhost:3000/images/image-7.webp"
    },
    {
        "id": "8",
        "url": "http://localhost:3000/images/image-8.webp"
    },
    {
        "id": "9",
        "url": "http://localhost:3000/images/image-9.webp"
    },
    {
        "id": "10",
        "url": "http://localhost:3000/images/image-10.jpeg"
    },
    {
        "id": "11",
        "url": "http://localhost:3000/images/image-11.jpeg"
    }
]